{
  "delegation": {
    "name": "العمران الاعلى",
    "code": "56"
  },
  "circonscription": {
    "name": "تونس 2",
    "code": "112"
  },
  "bureau_vote": {
    "name": "ALL",
    "code": "9999"
  },
  "centre_vote": {
    "name": "م إبتدائية الشابي - العمران الاعلى",
    "code": "003"
  },
  "resultat": {
    "listes": [
      {
        "num": 54,
        "pourcentage": 40.75027583670467,
        "vote": 1108,
        "name": "قائمة حزب حركة النهضة"
      },
      {
        "num": 78,
        "pourcentage": 17.24898859874954,
        "vote": 469,
        "name": "قائمة حزب المؤتمر من أجل الجمهورية"
      },
      {
        "num": 72,
        "pourcentage": 11.62191982346451,
        "vote": 316,
        "name": "قائمة حزب التكتل"
      },
      {
        "num": 79,
        "pourcentage": 3.310040456050018,
        "vote": 90,
        "name": "قائمة الحزب الديمقراطي التقدمي"
      },
      {
        "num": 70,
        "pourcentage": 2.758367046708349,
        "vote": 75,
        "name": "قائمة القطب الديمقراطي الحداثي"
      },
      {
        "num": 34,
        "pourcentage": 2.2434718646561236,
        "vote": 61,
        "name": "قائمة حزب الأمة الديمقراطي الأجتماعي"
      },
      {
        "num": 3,
        "pourcentage": 1.986024273630011,
        "vote": 54,
        "name": "قائمة حزب العمال الشيوعى التونسي(البديل الثوري)"
      },
      {
        "num": 16,
        "pourcentage": 1.5079073188672305,
        "vote": 41,
        "name": "قائمة الائتلاف الديمقراطي المستقل-طريق السلامة"
      },
      {
        "num": 38,
        "pourcentage": 1.471129091577786,
        "vote": 40,
        "name": "قائمة حزب المبادرة"
      },
      {
        "num": 40,
        "pourcentage": 1.4343508642883414,
        "vote": 39,
        "name": "قائمة العريضة الشعبية للحرية والعدالة والتنمية"
      },
      {
        "num": 43,
        "pourcentage": 1.4343508642883414,
        "vote": 39,
        "name": "قائمة حزب آفاق تونس"
      },
      {
        "num": 80,
        "pourcentage": 0.9562339095255609,
        "vote": 26,
        "name": "القائمة المستقلة دستورنا"
      },
      {
        "num": 5,
        "pourcentage": 0.7723427730783377,
        "vote": 21,
        "name": "قائمة الحزب الإصلاحي الدستوري"
      },
      {
        "num": 58,
        "pourcentage": 0.735564545788893,
        "vote": 20,
        "name": "قائمة حركة البعث"
      },
      {
        "num": 50,
        "pourcentage": 0.47811695476278043,
        "vote": 13,
        "name": "قائمة حركة الديمقراطية والتنمية"
      },
      {
        "num": 75,
        "pourcentage": 0.4413387274733358,
        "vote": 12,
        "name": "قائمة الاتحاد الوطني الحر"
      },
      {
        "num": 9,
        "pourcentage": 0.4413387274733358,
        "vote": 12,
        "name": "قائمة حزب الاتحاد الديمقراطي الوحدوي"
      },
      {
        "num": 52,
        "pourcentage": 0.40456050018389117,
        "vote": 11,
        "name": "قائمة المستقلة لتونس الغد"
      },
      {
        "num": 18,
        "pourcentage": 0.40456050018389117,
        "vote": 11,
        "name": "قائمة البديل للإصلاح"
      },
      {
        "num": 20,
        "pourcentage": 0.3677822728944465,
        "vote": 10,
        "name": "قائمة حزب الوفاق الجمهوري"
      },
      {
        "num": 64,
        "pourcentage": 0.3677822728944465,
        "vote": 10,
        "name": "قائمة العمل والإصلاح"
      },
      {
        "num": 11,
        "pourcentage": 0.3677822728944465,
        "vote": 10,
        "name": "قائمة حزب المجد"
      },
      {
        "num": 56,
        "pourcentage": 0.2942258183155572,
        "vote": 8,
        "name": "قائمة حركة الشعب"
      },
      {
        "num": 74,
        "pourcentage": 0.2942258183155572,
        "vote": 8,
        "name": "قائمة ائتلاف الشباب التونسي"
      },
      {
        "num": 1,
        "pourcentage": 0.2942258183155572,
        "vote": 8,
        "name": "قائمة الحزب التونسي"
      },
      {
        "num": 10,
        "pourcentage": 0.2942258183155572,
        "vote": 8,
        "name": "قائمة حزب الأحرار التونسي"
      },
      {
        "num": 61,
        "pourcentage": 0.2942258183155572,
        "vote": 8,
        "name": "قائمة الائتلاف التحرري"
      },
      {
        "num": 13,
        "pourcentage": 0.2942258183155572,
        "vote": 8,
        "name": "قائمة ائتلاف الكرامة"
      },
      {
        "num": 44,
        "pourcentage": 0.25744759102611253,
        "vote": 7,
        "name": "قائمة حركة الشعب الوحدوية التقدمية"
      },
      {
        "num": 31,
        "pourcentage": 0.25744759102611253,
        "vote": 7,
        "name": "قائمة شباب تونس"
      },
      {
        "num": 47,
        "pourcentage": 0.25744759102611253,
        "vote": 7,
        "name": "قائمة التآلف الجمهوري"
      },
      {
        "num": 63,
        "pourcentage": 0.25744759102611253,
        "vote": 7,
        "name": "قائمة حركة مواطنة"
      },
      {
        "num": 23,
        "pourcentage": 0.25744759102611253,
        "vote": 7,
        "name": "قائمة لنواصل الثورة"
      },
      {
        "num": 60,
        "pourcentage": 0.25744759102611253,
        "vote": 7,
        "name": "قائمة الأمل والوفاء للشهداء"
      },
      {
        "num": 12,
        "pourcentage": 0.2206693637366679,
        "vote": 6,
        "name": "قائمة الأمان"
      },
      {
        "num": 14,
        "pourcentage": 0.2206693637366679,
        "vote": 6,
        "name": "قائمة الوحدة الوطنية"
      },
      {
        "num": 41,
        "pourcentage": 0.2206693637366679,
        "vote": 6,
        "name": "قائمة حزب الخضر للتقدم (الخضر)"
      },
      {
        "num": 46,
        "pourcentage": 0.2206693637366679,
        "vote": 6,
        "name": "قائمة حزب العمل التونسي"
      },
      {
        "num": 28,
        "pourcentage": 0.2206693637366679,
        "vote": 6,
        "name": "قائمة الحزب الشعبي للحرية والتقدم"
      },
      {
        "num": 65,
        "pourcentage": 0.2206693637366679,
        "vote": 6,
        "name": "قائمة الاختلاف والتواصل"
      },
      {
        "num": 59,
        "pourcentage": 0.18389113644722324,
        "vote": 5,
        "name": "قائمة الاتحاد الشعبي الجمهوري"
      },
      {
        "num": 15,
        "pourcentage": 0.18389113644722324,
        "vote": 5,
        "name": "قائمة حزب العمل الوطني الديمقراطي"
      },
      {
        "num": 30,
        "pourcentage": 0.18389113644722324,
        "vote": 5,
        "name": "قائمة حزب العدل و التنمية"
      },
      {
        "num": 19,
        "pourcentage": 0.1471129091577786,
        "vote": 4,
        "name": "قائمة حركة الوحدة الشعبية"
      },
      {
        "num": 25,
        "pourcentage": 0.1471129091577786,
        "vote": 4,
        "name": "قائمة الشعب أراد الحياة"
      },
      {
        "num": 33,
        "pourcentage": 0.1471129091577786,
        "vote": 4,
        "name": "قائمة البيئة و الاقتصاد الأخضر"
      },
      {
        "num": 6,
        "pourcentage": 0.1471129091577786,
        "vote": 4,
        "name": "قائمة المستقلون الديمقراطيون"
      },
      {
        "num": 53,
        "pourcentage": 0.1471129091577786,
        "vote": 4,
        "name": "قائمة حزب تونس الخضراء"
      },
      {
        "num": 42,
        "pourcentage": 0.1471129091577786,
        "vote": 4,
        "name": "قائمة حزب الانفتاح والوفاء"
      },
      {
        "num": 7,
        "pourcentage": 0.1471129091577786,
        "vote": 4,
        "name": "قائمة الانتصار لتونس"
      },
      {
        "num": 4,
        "pourcentage": 0.1471129091577786,
        "vote": 4,
        "name": "قائمة من أجل جبهة وطنية تونسية"
      },
      {
        "num": 8,
        "pourcentage": 0.1471129091577786,
        "vote": 4,
        "name": "قائمة تونس الأمل"
      },
      {
        "num": 36,
        "pourcentage": 0.1471129091577786,
        "vote": 4,
        "name": "قائمة حزب العدالة الاجتماعي الديمقراطي (ناخو حقي)"
      },
      {
        "num": 29,
        "pourcentage": 0.11033468186833395,
        "vote": 3,
        "name": "قائمة المنارة"
      },
      {
        "num": 22,
        "pourcentage": 0.11033468186833395,
        "vote": 3,
        "name": "قائمة حزب المسار التونسي"
      },
      {
        "num": 45,
        "pourcentage": 0.11033468186833395,
        "vote": 3,
        "name": "قائمة المشاريع الكبرى"
      },
      {
        "num": 35,
        "pourcentage": 0.11033468186833395,
        "vote": 3,
        "name": "قائمة إرادة الحياة"
      },
      {
        "num": 68,
        "pourcentage": 0.11033468186833395,
        "vote": 3,
        "name": "قائمة حزب التقدم"
      },
      {
        "num": 27,
        "pourcentage": 0.11033468186833395,
        "vote": 3,
        "name": "قائمة الحركة الديمقراطية للإصلاح و البناء"
      },
      {
        "num": 76,
        "pourcentage": 0.11033468186833395,
        "vote": 3,
        "name": "قائمة التيار الوطني المستقل تونس للجميع"
      },
      {
        "num": 73,
        "pourcentage": 0.11033468186833395,
        "vote": 3,
        "name": "قائمة الحركة الإصلاحية التونسية"
      },
      {
        "num": 69,
        "pourcentage": 0.0735564545788893,
        "vote": 2,
        "name": "قائمة الحزب اللبرالي المغاربي"
      },
      {
        "num": 55,
        "pourcentage": 0.0735564545788893,
        "vote": 2,
        "name": "قائمة المستقلة للحداثة والتقدم"
      },
      {
        "num": 24,
        "pourcentage": 0.0735564545788893,
        "vote": 2,
        "name": "قائمة المشروع"
      },
      {
        "num": 37,
        "pourcentage": 0.0735564545788893,
        "vote": 2,
        "name": "قائمة حركة الديمقراطيين الاشتراكيين"
      },
      {
        "num": 66,
        "pourcentage": 0.0735564545788893,
        "vote": 2,
        "name": "قائمة الحزب الديمقراطي للعدالة والرخاء"
      },
      {
        "num": 48,
        "pourcentage": 0.0735564545788893,
        "vote": 2,
        "name": "قائمة حزب الوحدة الشعبية"
      },
      {
        "num": 49,
        "pourcentage": 0.0735564545788893,
        "vote": 2,
        "name": "قائمة الحزب الدستوري الجديد"
      },
      {
        "num": 21,
        "pourcentage": 0.0735564545788893,
        "vote": 2,
        "name": "قائمة حزب الثقافة و العمل"
      },
      {
        "num": 2,
        "pourcentage": 0.0735564545788893,
        "vote": 2,
        "name": "قائمة حركة الثقافة و التنوع"
      },
      {
        "num": 51,
        "pourcentage": 0.03677822728944465,
        "vote": 1,
        "name": "قائمة الياسمين المستقلة لتحقيق أهداف الثورة"
      },
      {
        "num": 57,
        "pourcentage": 0.03677822728944465,
        "vote": 1,
        "name": "قائمة حزب الأمانة"
      },
      {
        "num": 77,
        "pourcentage": 0.03677822728944465,
        "vote": 1,
        "name": "قائمة الأمل للجميع"
      },
      {
        "num": 39,
        "pourcentage": 0.03677822728944465,
        "vote": 1,
        "name": "قائمة حزب الإصلاح و التنمية"
      },
      {
        "num": 17,
        "pourcentage": 0.03677822728944465,
        "vote": 1,
        "name": "قائمة حزب تونس الكرامة"
      },
      {
        "num": 62,
        "pourcentage": 0.03677822728944465,
        "vote": 1,
        "name": "قائمة حزب التحالف الوطني للسلم والنماء"
      },
      {
        "num": 67,
        "pourcentage": 0.03677822728944465,
        "vote": 1,
        "name": "قائمة الحركة التونسية للعمل المغاربي"
      },
      {
        "num": 26,
        "pourcentage": 0.03677822728944465,
        "vote": 1,
        "name": "قائمة الورقة الخضراء"
      },
      {
        "num": 71,
        "pourcentage": 0,
        "vote": 0,
        "name": "قائمة لننتصر للغد"
      },
      {
        "num": 32,
        "pourcentage": 0,
        "vote": 0,
        "name": "قائمة تونس الحديثة"
      }
    ],
    "electeurs": {
      "votant": 2834,
      "enregistre": 3325
    },
    "bulletins": {
      "endommage": 8,
      "dans_urne": 2834,
      "correct": 2719,
      "delivre": 3694,
      "non_utilise": 852,
      "blancs": 60,
      "annule": 55
    }
  }
}