{
  "delegation": {
    "name": "فوار",
    "code": "56"
  },
  "circonscription": {
    "name": "قبلي",
    "code": "630"
  },
  "bureau_vote": {
    "name": "ALL",
    "code": "9999"
  },
  "centre_vote": {
    "name": "ALL",
    "code": "9999"
  },
  "resultat": {
    "listes": [
      {
        "num": 23,
        "pourcentage": 34.72203250922005,
        "vote": 2542,
        "name": "قائمة حركة النهضة"
      },
      {
        "num": 22,
        "pourcentage": 16.199972681327687,
        "vote": 1186,
        "name": "قائمة العريضة الشعبية للحرية والعدالة والتنمية"
      },
      {
        "num": 8,
        "pourcentage": 14.834039065701408,
        "vote": 1086,
        "name": "قائمة حزب المؤتمر من أجل الجمهورية"
      },
      {
        "num": 24,
        "pourcentage": 6.611118699631198,
        "vote": 484,
        "name": "قائمة إرادة الحياة"
      },
      {
        "num": 15,
        "pourcentage": 3.3192186859718613,
        "vote": 243,
        "name": "قائمة الوفــاء"
      },
      {
        "num": 16,
        "pourcentage": 3.1143286436279194,
        "vote": 228,
        "name": "قائمة الكرامة"
      },
      {
        "num": 12,
        "pourcentage": 2.9230979374402404,
        "vote": 214,
        "name": "قائمة المبادرة الحرّة"
      },
      {
        "num": 1,
        "pourcentage": 2.813823248190138,
        "vote": 206,
        "name": "قائمة الحزب الديمقراطي التقدمي"
      },
      {
        "num": 9,
        "pourcentage": 2.0489004234394206,
        "vote": 150,
        "name": "قائمة الاتحاد الوطني الحر"
      },
      {
        "num": 3,
        "pourcentage": 1.7074170195328506,
        "vote": 125,
        "name": "قائمة تونس لنا ونحن لها"
      },
      {
        "num": 17,
        "pourcentage": 1.4205709602513317,
        "vote": 104,
        "name": "قائمة التقدمية المستقلة"
      },
      {
        "num": 2,
        "pourcentage": 1.4205709602513317,
        "vote": 104,
        "name": "قائمة حزب العمال الشيوعي التونسي (البديل الثوري)"
      },
      {
        "num": 5,
        "pourcentage": 1.2156809179073897,
        "vote": 89,
        "name": "قائمة حزب التكتل"
      },
      {
        "num": 10,
        "pourcentage": 1.133724900969813,
        "vote": 83,
        "name": "قائمة حركة الشعب الوحدوية التقدمية"
      },
      {
        "num": 7,
        "pourcentage": 1.1064062286572873,
        "vote": 81,
        "name": "قائمة 14جانفي"
      },
      {
        "num": 6,
        "pourcentage": 1.0244502117197103,
        "vote": 75,
        "name": "قائمة القطب الديمقراطي الحداثي"
      },
      {
        "num": 4,
        "pourcentage": 0.8059008332195056,
        "vote": 59,
        "name": "قائمة حركة الديمقراطيين الاشتراكيين"
      },
      {
        "num": 11,
        "pourcentage": 0.7512634885944544,
        "vote": 55,
        "name": "قائمة حزب الوحدة الشعبية"
      },
      {
        "num": 13,
        "pourcentage": 0.5463734462505122,
        "vote": 40,
        "name": "قائمة حزب الخضر للتقدّم (الخضر)"
      },
      {
        "num": 26,
        "pourcentage": 0.5190547739379866,
        "vote": 38,
        "name": "قائمة الإصلاح والمصالحة"
      },
      {
        "num": 21,
        "pourcentage": 0.3824614123753586,
        "vote": 28,
        "name": "قائمة الكادحة المستقلة"
      },
      {
        "num": 25,
        "pourcentage": 0.3551427400628329,
        "vote": 26,
        "name": "قائمة الاتحاد الديمقراطي الوحدوي"
      },
      {
        "num": 14,
        "pourcentage": 0.3551427400628329,
        "vote": 26,
        "name": "قائمة التآلف الجمهوري"
      },
      {
        "num": 18,
        "pourcentage": 0.2595273869689933,
        "vote": 19,
        "name": "قائمة الفلسفة"
      },
      {
        "num": 19,
        "pourcentage": 0.21854937850020487,
        "vote": 16,
        "name": "قائمة حزب التحالف الوطني للسلم والنماء"
      },
      {
        "num": 20,
        "pourcentage": 0.1912307061876793,
        "vote": 14,
        "name": "قائمة الوحدة الوطنية"
      }
    ],
    "electeurs": {
      "votant": 7892,
      "enregistre": 11115
    },
    "bulletins": {
      "endommage": 28,
      "dans_urne": 7892,
      "correct": 7321,
      "delivre": 10202,
      "non_utilise": 2281,
      "blancs": 258,
      "annule": 313
    }
  }
}