{
  "delegation": {
    "name": "نفطة",
    "code": "54"
  },
  "circonscription": {
    "name": "توزر",
    "code": "620"
  },
  "bureau_vote": {
    "name": "ALL",
    "code": "9999"
  },
  "centre_vote": {
    "name": "م إبتدائية الخضر بن الحسين نفطة",
    "code": "007"
  },
  "resultat": {
    "listes": [
      {
        "num": 29,
        "pourcentage": 38.74107722258274,
        "vote": 597,
        "name": "قائمة حركة النهضة"
      },
      {
        "num": 11,
        "pourcentage": 18.10512654120701,
        "vote": 279,
        "name": "قائمة الكرامة الوطنية"
      },
      {
        "num": 19,
        "pourcentage": 7.397793640493186,
        "vote": 114,
        "name": "قائمة الوفاء للشهداء"
      },
      {
        "num": 1,
        "pourcentage": 4.3478260869565215,
        "vote": 67,
        "name": "قائمة حركة الشعب الوحدوية التقدمية"
      },
      {
        "num": 7,
        "pourcentage": 3.958468526930565,
        "vote": 61,
        "name": "قائمة القطب الديمقراطي الحداثي"
      },
      {
        "num": 23,
        "pourcentage": 2.9850746268656714,
        "vote": 46,
        "name": "قائمة الحزب الديمقراطي التقدمي"
      },
      {
        "num": 2,
        "pourcentage": 2.855288773523686,
        "vote": 44,
        "name": "قائمة حزب المؤتمر من أجل الجمهورية"
      },
      {
        "num": 25,
        "pourcentage": 2.6606099935107075,
        "vote": 41,
        "name": "قائمة العريضة الشعبية للحرية والعدالة والتنمية"
      },
      {
        "num": 10,
        "pourcentage": 2.2712524334847504,
        "vote": 35,
        "name": "قائمة حزب الاتحاد الوطني الحر"
      },
      {
        "num": 38,
        "pourcentage": 1.7521090201168072,
        "vote": 27,
        "name": "قائمة حزب التكتل"
      },
      {
        "num": 34,
        "pourcentage": 1.6872160934458142,
        "vote": 26,
        "name": "قائمة المستقلون لمستقبل الإصلاح والتنمية"
      },
      {
        "num": 32,
        "pourcentage": 1.0382868267358858,
        "vote": 16,
        "name": "قائمة حرية وتضامن"
      },
      {
        "num": 3,
        "pourcentage": 0.8436080467229071,
        "vote": 13,
        "name": "قائمة التأسيس والبناء"
      },
      {
        "num": 24,
        "pourcentage": 0.7787151200519143,
        "vote": 12,
        "name": "قائمة الاتحاد الديمقراطي الوحدوي"
      },
      {
        "num": 9,
        "pourcentage": 0.7787151200519143,
        "vote": 12,
        "name": "قائمة صوت شباب الجريد الأحرار"
      },
      {
        "num": 12,
        "pourcentage": 0.7787151200519143,
        "vote": 12,
        "name": "قائمة حزب التحالف الوطني للسلم والنماء"
      },
      {
        "num": 28,
        "pourcentage": 0.7787151200519143,
        "vote": 12,
        "name": "قائمة حزب العمال الشيوعي التونسي (البديل الثـوري)"
      },
      {
        "num": 39,
        "pourcentage": 0.7138221933809215,
        "vote": 11,
        "name": "قائمة اتحاد الشباب المستقل"
      },
      {
        "num": 15,
        "pourcentage": 0.7138221933809215,
        "vote": 11,
        "name": "القائمة حزب تونس الخضراء"
      },
      {
        "num": 13,
        "pourcentage": 0.6489292667099287,
        "vote": 10,
        "name": "قائمة حركة الديمقراطية والتنمية"
      },
      {
        "num": 22,
        "pourcentage": 0.6489292667099287,
        "vote": 10,
        "name": "قائمة حركة الشعب"
      },
      {
        "num": 31,
        "pourcentage": 0.5191434133679429,
        "vote": 8,
        "name": "قائمة الحزب الليبرالي المغاربي"
      },
      {
        "num": 18,
        "pourcentage": 0.5191434133679429,
        "vote": 8,
        "name": "قائمة حركة الديمقراطيين الاشتراكيين"
      },
      {
        "num": 27,
        "pourcentage": 0.45425048669695006,
        "vote": 7,
        "name": "قائمة الخـــلاص"
      },
      {
        "num": 6,
        "pourcentage": 0.3893575600259572,
        "vote": 6,
        "name": "قائمة أبو القاسم الشابي"
      },
      {
        "num": 20,
        "pourcentage": 0.3893575600259572,
        "vote": 6,
        "name": "قائمة حركة الديمقراطيين الاشتراكيين المؤتمر التاسع"
      },
      {
        "num": 30,
        "pourcentage": 0.3893575600259572,
        "vote": 6,
        "name": "قائمة حزب الأمة الديمقراطي الاجتماعي"
      },
      {
        "num": 8,
        "pourcentage": 0.32446463335496434,
        "vote": 5,
        "name": "قائمة حزب الثقافة والعمل"
      },
      {
        "num": 4,
        "pourcentage": 0.32446463335496434,
        "vote": 5,
        "name": "قائمة حزب الوحدة الشعبية"
      },
      {
        "num": 21,
        "pourcentage": 0.25957170668397145,
        "vote": 4,
        "name": "قائمة حركة مواطنة"
      },
      {
        "num": 35,
        "pourcentage": 0.25957170668397145,
        "vote": 4,
        "name": "قائمة الوحدة الوطنية"
      },
      {
        "num": 14,
        "pourcentage": 0.25957170668397145,
        "vote": 4,
        "name": "قائمة حزب الإصلاح والتنمية"
      },
      {
        "num": 37,
        "pourcentage": 0.25957170668397145,
        "vote": 4,
        "name": "قائمة حزب المسار التونسي"
      },
      {
        "num": 5,
        "pourcentage": 0.25957170668397145,
        "vote": 4,
        "name": "قائمة حزب الانفتاح والوفاء"
      },
      {
        "num": 17,
        "pourcentage": 0.25957170668397145,
        "vote": 4,
        "name": "قائمة الخطاف"
      },
      {
        "num": 33,
        "pourcentage": 0.1946787800129786,
        "vote": 3,
        "name": "قائمة حركة الوطنيين الديمقراطيين"
      },
      {
        "num": 16,
        "pourcentage": 0.1946787800129786,
        "vote": 3,
        "name": "قائمة الاتحاد والعدالة"
      },
      {
        "num": 40,
        "pourcentage": 0.1946787800129786,
        "vote": 3,
        "name": "قائمة الائتلاف الديمقراطي المستقل - طريق السلامة -"
      },
      {
        "num": 36,
        "pourcentage": 0.06489292667099286,
        "vote": 1,
        "name": "قائمة حزب الوفاء لتونس"
      },
      {
        "num": 26,
        "pourcentage": 0,
        "vote": 0,
        "name": "قائمة الخير"
      }
    ],
    "electeurs": {
      "votant": 1680,
      "enregistre": 1938
    },
    "bulletins": {
      "endommage": 2,
      "dans_urne": 1680,
      "correct": 1541,
      "delivre": 2235,
      "non_utilise": 552,
      "blancs": 64,
      "annule": 75
    }
  }
}